tna_utilities/__init__.py
tna_utilities/currency.py
tna_utilities/datetime.py
tna_utilities/string.py
tna_utilities/url.py
tna_utilities-1.1.0.dist-info/licenses/LICENCE
tna_utilities-1.1.0.dist-info/METADATA
tna_utilities-1.1.0.dist-info/WHEEL
tna_utilities-1.1.0.dist-info/top_level.txt
tna_utilities-1.1.0.dist-info/RECORD
