Metadata-Version: 2.4
Name: tna-utilities
Version: 1.1.0
Summary: A library of common National Archives Python functions
Home-page: https://github.com/nationalarchives/python-utilities
Author: Andrew Hosgood
Author-email: andrew.hosgood@nationalarchives.gov.uk
Project-URL: Bug Tracker, https://github.com/nationalarchives/python-utilities/issues
Classifier: Programming Language :: Python :: 3
Classifier: License :: OSI Approved :: MIT License
Classifier: Operating System :: OS Independent
Classifier: Environment :: Web Environment
Classifier: Intended Audience :: Developers
Requires-Python: >=3.10
License-File: LICENCE
Dynamic: author
Dynamic: author-email
Dynamic: classifier
Dynamic: description
Dynamic: description-content-type
Dynamic: home-page
Dynamic: license-file
Dynamic: project-url
Dynamic: requires-python
Dynamic: summary
